{
  "seasons": {
    "spring": "March 21 - June 20",
    "summer": "June 21 - September 20",
    "autumn": "September 21 - December 20",
    "winter": "December 21 - March 20"
  },
  "season_names": {
    "en": {
      "spring": "Spring",
      "summer": "Summer",
      "autumn": "Autumn",
      "winter": "Winter"
    },
    "ar": {
      "spring": "الربيع",
      "summer": "الصيف",
      "autumn": "الخريف",
      "winter": "الشتاء"
    }
  },
  "weather_month": {
    "en": {
      "01": "Peak cold",
      "02": "End of cold",
      "03": "Warming begins",
      "04": "Mild and fresh",
      "05": "Heat begins",
      "06": "Extreme heat",
      "07": "Peak heat",
      "08": "Heat eases",
      "09": "End of summer",
      "10": "Pleasant",
      "11": "Mild and cool",
      "12": "Cold begins"
    },
    "ar": {
      "01": "قمة البرد",
      "02": "نهاية البرد",
      "03": "بداية الاحترار",
      "04": "معتدل ومنعش",
      "05": "بداية الحرارة",
      "06": "حرارة شديدة",
      "07": "ذروة الحرارة",
      "08": "انحسار الحرارة",
      "09": "نهاية الصيف",
      "10": "معتدل",
      "11": "معتدل وبارد",
      "12": "بداية البرد"
    }
  }
}
